{
	"sn": "facebook",
	"lastEventDate": "15.12.2022 11:42 9 A 12 DIAS",
	"status": 2,
	"id": "100088559736996",
	"name": "fontanaju",
	"amountFriends": "113",
	"screenname": "Juliana Fontes",
	"birthdate": "1983 November 18",
	"country": "",
	"isAvatarExists": false,
	"cookie": [
		{
			"domain": ".facebook.com",
			"expirationDate": 1704935776.512699,
			"hostOnly": false,
			"httpOnly": true,
			"name": "dbln",
			"path": "/login/device-based/",
			"sameSite": "no_restriction",
			"secure": true,
			"session": false,
			"storeId": "0",
			"value": "%7B%22100088559736996%22%3A%225mQPeSsD%22%7D"
		},
		{
			"domain": ".facebook.com",
			"expirationDate": 1704934467.003781,
			"hostOnly": false,
			"httpOnly": true,
			"name": "sb",
			"path": "/",
			"sameSite": "no_restriction",
			"secure": true,
			"session": false,
			"storeId": "0",
			"value": "0-OPY0ERoQtlwebpBFf-0b-g"
		},
		{
			"domain": ".facebook.com",
			"expirationDate": 1704934356.382299,
			"hostOnly": false,
			"httpOnly": true,
			"name": "datr",
			"path": "/",
			"sameSite": "no_restriction",
			"secure": true,
			"session": false,
			"storeId": "0",
			"value": "0-OPYz3MzcN9CHGDgqdichBO"
		},
		{
			"domain": ".facebook.com",
			"expirationDate": 1702639370.553037,
			"hostOnly": false,
			"httpOnly": false,
			"name": "c_user",
			"path": "/",
			"sameSite": "no_restriction",
			"secure": true,
			"session": false,
			"storeId": "0",
			"value": "100088559736996"
		},
		{
			"domain": ".facebook.com",
			"expirationDate": 1671708300,
			"hostOnly": false,
			"httpOnly": false,
			"name": "wd",
			"path": "/",
			"sameSite": "lax",
			"secure": true,
			"session": false,
			"storeId": "0",
			"value": "1440x712"
		},
		{
			"domain": ".facebook.com",
			"expirationDate": 1702639370.553075,
			"hostOnly": false,
			"httpOnly": true,
			"name": "xs",
			"path": "/",
			"sameSite": "no_restriction",
			"secure": true,
			"session": false,
			"storeId": "0",
			"value": "2%3ALuTZFeSEiXBKwA%3A2%3A1670374464%3A-1%3A2117%3A%3AAcVzhgZsiUy-_ExvcmeaYRzkdaDZLFg1ksn1TN4xPA"
		},
		{
			"domain": ".facebook.com",
			"expirationDate": 1678879369.55309,
			"hostOnly": false,
			"httpOnly": true,
			"name": "fr",
			"path": "/",
			"sameSite": "no_restriction",
			"secure": true,
			"session": false,
			"storeId": "0",
			"value": "0yEhBGfa9GUi44aWd.AWWpaPOg7AEljW6vbIkX_DObxkw.BjmwOJ.uH.AAA.0.0.BjmwOJ.AWVUAPWuL_Q"
		},
		{
			"domain": ".facebook.com",
			"hostOnly": false,
			"httpOnly": false,
			"name": "presence",
			"path": "/",
			"sameSite": "unspecified",
			"secure": true,
			"session": true,
			"storeId": "0",
			"value": "C%7B%22t3%22%3A%5B%5D%2C%22utc3%22%3A1671103457366%2C%22v%22%3A1%7D"
		}
	]
}